karton_mwdb_reporter-1.3.0-nspkg.pth
karton/mwdb_reporter/__init__.py
karton/mwdb_reporter/__main__.py
karton/mwdb_reporter/__version__.py
karton/mwdb_reporter/mwdb_reporter.py
karton_mwdb_reporter-1.3.0.dist-info/LICENSE
karton_mwdb_reporter-1.3.0.dist-info/METADATA
karton_mwdb_reporter-1.3.0.dist-info/WHEEL
karton_mwdb_reporter-1.3.0.dist-info/entry_points.txt
karton_mwdb_reporter-1.3.0.dist-info/namespace_packages.txt
karton_mwdb_reporter-1.3.0.dist-info/top_level.txt
karton_mwdb_reporter-1.3.0.dist-info/RECORD
