Metadata-Version: 2.1
Name: karton-mwdb-reporter
Version: 1.3.0
Summary: Karton service that uploads analyzed artifacts and metadata to MWDB Core
Home-page: https://github.com/CERT-Polska/karton-mwdb-reporter/
License: UNKNOWN
Platform: UNKNOWN
Classifier: Programming Language :: Python
Classifier: Operating System :: OS Independent
License-File: LICENSE
Requires-Dist: karton-core (<6.0.0,>=5.0.0)
Requires-Dist: mwdblib (>=4.3.0)
